{
  "global": {
    "blue": {
      "value": "#66ccff",
      "type": "color"
    },
    "red": {
      "value": "#ff5050",
      "type": "color"
    },
    "green": {
      "value": "#009900",
      "type": "color"
    },
    "yellow": {
      "value": "#fffaeb",
      "type": "color"
    }
  },
  "color": {
    "blue": {
      "value": "#0099ff",
      "type": "color"
    },
    "Green": {
      "value": "#bae3cb",
      "type": "color"
    },
    "brown": {
      "value": "#e8dbcc",
      "type": "color"
    }
  },
  "Color2": {
    "colors": {
      "button": {
        "background": {
          "primary": {
            "value": "#e8dbcc",
            "type": "color"
          },
          "secondary": {
            "value": "#a37038",
            "type": "color"
          }
        }
      }
    }
  }
}